{
  "hash": "6499dc37",
  "browserHash": "272814de",
  "optimized": {
    "vue": {
      "src": "../../../../node_modules/vue/dist/vue.runtime.esm-bundler.js",
      "file": "vue.js",
      "fileHash": "9964c29a",
      "needsInterop": false
    },
    "anu-vue": {
      "src": "../../../../node_modules/anu-vue/dist/anu-vue.js",
      "file": "anu-vue.js",
      "fileHash": "3d30536a",
      "needsInterop": false
    }
  },
  "chunks": {
    "chunk-R647EDCJ": {
      "file": "chunk-R647EDCJ.js"
    }
  }
}